[{"id":1,"name":"connector-tw","label":"Tw Connector","type":"Connector","imageUrl":"","description":"","confsPath":"/confs/connector-tw","enabled":true,"confs":{"TwStreamConnector.properties":{"name":"TwStreamConnector.properties","sections":[{"name":"TWITTER CONFIGURATIONS","label":"Twitter Configurations","description":"mandatory otherwise the connector won\u0027t work","props":[{"name":"twConsumerKey","label":"twConsumerKey","value":"dasdassfteta","description":"Twitter consumer key","required":true},{"name":"twConsumerSecret","label":"twConsumerSecret","value":"","description":"Twitter consumer secret","required":true},{"name":"twToken","label":"twToken","value":"","description":"Twitter token","required":true},{"name":"twTokenSecret","label":"twTokenSecret","value":"","description":"Twitter token secret","required":true}]},{"name":"NODE  CONFIGURATIONS","label":"Node Configurations","description":"Configurations related to the master node that hosts the application","props":[{"name":"nodeName","label":"Node Name","value":"","description":"Name of the node that hosts the application","required":true},{"name":"proxyHost","label":"Proxy Host","value":"","description":"valorize if a proxy is used for outbound connections","required":false},{"name":"proxyPort","label":"Proxy Port","value":"","description":"valorize if a proxy is used for outbound connections","required":false}]},{"name":"SPARK  CONFIGURATIONS","label":"Spark Configurations","description":"Configurations related to Spark","props":[{"name":"numMaxCore","label":"num Max Core","value":"2","description":"max number of cores that can be used for this application","required":true},{"name":"checkpointDir","label":"checkpoint Directory","value":"/tmp/checkpoints/tw-connector","description":"","required":true},{"name":"sparkBatchDurationMillis","label":"sparkBatchDurationMillis","value":"3000","description":"duration of a spark batch (consider that objects will be sent on the bus for each batch)","required":true},{"name":"sparkCleanTTL","label":"sparkCleanTTL","value":"480000","description":"","required":true},{"name":"twitterInserterWindowDuration","label":"twitterInserterWindowDuration","value":"60000","description":"time window on which data will be saved","required":true},{"name":"twitterInserterWindowSlidingInterval","label":"twitterInserterWindowSlidingInterval","value":"60000","description":"","required":true}]},{"name":"APP   CONFIGURATIONS","label":"App Configurations","description":"Configurations related to App","props":[{"name":"serverPort","label":"server listening Port","value":"8089","description":"Jetty server port","required":true},{"name":"savePartitions","label":"savePartitions","value":"2","description":"the number of partitions to coalesce before save","required":true},{"name":"dataOutputFolder","label":"dataOutputFolder","value":"/data","description":"the folder where data has to be saved","required":true},{"name":"dataRootFolder","label":"dataRootFolder","value":"raw","description":"Example dataOutputFolder\u003dfile://tmp/data and dataRootFolder\u003draw will save data on file://tmp/data/raw/...","required":true},{"name":"daoClass","label":"daoClass","value":"","description":"class for the custom dao if you don\u0027t want to use the default one","required":true}]},{"name":"KAFKA CONFIGURATIONS","label":"Kafka Configurations","description":"Configurations related to Kafka bus","props":[{"name":"brokersList","label":"brokersList","value":"localhost:9092","description":"Kafka brokers list","required":true},{"name":"kafkaSerializationClass","label":"kafkaSerializationClass","value":"kafka.serializer.StringEncoder","description":"","required":true},{"name":"kafkaRequiredAcks","label":"kafkaRequiredAcks","value":"1","description":"tells Kafka that you want your Producer to require an acknowledgement from the Broker that the message was received.","required":true},{"name":"maxTotalConnections","label":"maxTotalConnections","value":"10","description":"number of connections for the connection pool","required":true},{"name":"maxIdleConnections","label":"maxIdleConnections","value":"10","description":"number of connections for the connection pool","required":true},{"name":"customProducerFactoryImpl","label":"customProducerFactoryImpl","value":"","description":"valorize if needed other implementation for connection to bus different than kafka","required":true}]}]},"log4j.properties":{"name":"log4j.properties","sections":[{"name":"Root logger option","label":"Root logger option","description":"","props":[{"name":"log4j.rootLogger","label":"log4j.rootLogger","value":"INFO, stdout","description":"","required":true},{"name":"log4j.logger.com.tilab.ca","label":"log4j.logger.com.tilab.ca","value":"INFO, stdout","description":"INFO, stdout","required":true}]},{"name":"stdout","label":"stdout","description":"Direct log messages to stdout","props":[{"name":"log4j.appender.stdout","label":"log4j.appender.stdout","value":"org.apache.log4j.ConsoleAppender","description":"","required":true},{"name":"log4j.appender.stdout.Target","label":"log4j.appender.stdout.Target","value":"System.out","description":"","required":true},{"name":"log4j.appender.stdout.layout","label":"log4j.appender.stdout.layout","value":"org.apache.log4j.PatternLayout","description":"","required":true},{"name":"log4j.appender.stdout.layout.ConversionPattern","label":"log4j.appender.stdout.layout.ConversionPattern","value":"%d{yyyy-MM-dd HH:mm:ss} %-5p %c{1}:%L - %m%n","description":"","required":true}]},{"name":"file","label":"file","description":"log messages to file","props":[{"name":"log4j.appender.file","label":"log4j.appender.file","value":"org.apache.log4j.RollingFileAppender","description":"","required":false},{"name":"log4j.appender.file.File","label":"log4j.appender.file.File","value":"","description":"","required":false},{"name":"log4j.appender.file.MaxFileSize","label":"log4j.appender.file.MaxFileSize","value":"100MB","description":"","required":false},{"name":"log4j.appender.file.MaxBackupIndex","label":"log4j.appender.file.MaxBackupIndex","value":"1","description":"","required":false},{"name":"log4j.appender.file.layout","label":"log4j.appender.file.layout","value":"org.apache.log4j.PatternLayout","description":"","required":false},{"name":"log4j.appender.file.layout.ConversionPattern","label":"log4j.appender.file.layout.ConversionPattern","value":"%d{yyyy-MM-dd HH:mm:ss} %-5p %c{1}:%L - %m%n","description":"","required":false}]},{"name":"sparklogger","label":"sparklogger","description":"log messages to sparklogger","props":[{"name":"log4j.appender.sparklogger","label":"log4j.appender.sparklogger","value":"org.apache.log4j.RollingFileAppender","description":"","required":false},{"name":"log4j.appender.sparklogger.File","label":"log4j.appender.sparklogger.File","value":"","description":"","required":false},{"name":"log4j.appender.sparklogger.MaxFileSize","label":"log4j.appender.sparklogger.MaxFileSize","value":"200MB","description":"","required":false},{"name":"log4j.appender.sparklogger.MaxBackupIndex","label":"log4j.appender.sparklogger.MaxBackupIndex","value":"1","description":"","required":false},{"name":"log4j.appender.sparklogger.layout","label":"log4j.appender.sparklogger.layout","value":"org.apache.log4j.PatternLayout","description":"","required":false},{"name":"log4j.appender.sparklogger.layout.ConversionPattern","label":"log4j.appender.sparklogger.layout.ConversionPattern","value":"%d{yyyy-MM-dd HH:mm:ss} %-5p %c{1}:%L - %m%n","description":"","required":false}]}]}}}]